capctl/__init__.py
capctl/__version__.py
capctl/app.py
capctl/cap_util.py
capctl/dev.py
capctl/dex.py
capctl/kfp_proxy.py
capctl/log.py
capctl/main.py
capctl/profile.py
capctl/project.py
capctl/quota.py
capctl/script.py
capctl/session.py
capctl/storage.py
capctl/user.py
capctl-1.0.0.dist-info/METADATA
capctl-1.0.0.dist-info/WHEEL
capctl-1.0.0.dist-info/entry_points.txt
capctl-1.0.0.dist-info/top_level.txt
capctl-1.0.0.dist-info/RECORD
