Metadata-Version: 2.1
Name: capctl
Version: 1.0.0
Summary: Command line tool for CAP
Home-page: https://gitlab.dudaji.com
Author: dudaji
Author-email: contact@dudaji.com
License: UNKNOWN
Platform: UNKNOWN
Classifier: Programming Language :: Python
Classifier: Programming Language :: Python :: 2
Classifier: Programming Language :: Python :: 2.7
Classifier: Programming Language :: Python :: 3
Classifier: Programming Language :: Python :: 3.5
Classifier: Programming Language :: Python :: 3.6
Classifier: Programming Language :: Python :: 3.7
Requires-Python: >=2.7, !=3.0.*, !=3.1.*, !=3.2.*, !=3.3.*, !=3.4.*
Requires-Dist: bcrypt (==3.2.0)
Requires-Dist: cachetools (==4.2.2)
Requires-Dist: certifi (==2020.12.5)
Requires-Dist: cffi (==1.14.5)
Requires-Dist: chardet (==4.0.0)
Requires-Dist: coloredlogs (==15.0)
Requires-Dist: fire (==0.3.1)
Requires-Dist: google-auth (==1.30.0)
Requires-Dist: humanfriendly (==9.1)
Requires-Dist: idna (==2.10)
Requires-Dist: kubernetes (==11.0.0)
Requires-Dist: oauthlib (==3.1.0)
Requires-Dist: pyasn1 (==0.4.8)
Requires-Dist: pyasn1-modules (==0.2.8)
Requires-Dist: pycparser (==2.20)
Requires-Dist: python-dateutil (==2.8.1)
Requires-Dist: PyYAML (==5.4.1)
Requires-Dist: requests (==2.25.1)
Requires-Dist: requests-oauthlib (==1.3.0)
Requires-Dist: rsa (==4.7.2)
Requires-Dist: six (==1.16.0)
Requires-Dist: termcolor (==1.1.0)
Requires-Dist: terminaltables (==3.1.0)
Requires-Dist: urllib3 (==1.26.4)
Requires-Dist: websocket-client (==0.59.0)
Requires-Dist: kfp (==1.6.6)
